litoid/__init__.py
litoid/__main__.py
litoid/app.py
litoid/io/__init__.py
litoid/io/dmx.py
litoid/io/hotkey.py
litoid/io/key_mouse.py
litoid/io/midi/__init__.py
litoid/io/midi/message.py
litoid/io/midi/midi.py
litoid/io/osc.py
litoid/io/player.py
litoid/io/recorder.py
litoid/io/track.py
litoid/litoid.py
litoid/log.py
litoid/scenes/__init__.py
litoid/scenes/compose.py
litoid/scenes/rgb_keyboard.py
litoid/state/__init__.py
litoid/state/instrument.py
litoid/state/instruments.py
litoid/state/lamp.py
litoid/state/level.py
litoid/state/scene.py
litoid/state/state.py
litoid/ui/__init__.py
litoid/ui/action.py
litoid/ui/canvas_window.py
litoid/ui/controller.py
litoid/ui/defaults.py
litoid/ui/drawing_canvas.py
litoid/ui/event.py
litoid/ui/layout.py
litoid/ui/model.py
litoid/ui/ui.py
litoid/ui/view.py
litoid/util/__init__.py
litoid/util/file.py
litoid/util/has_thread.py
litoid/util/is_running.py
litoid/util/play.py
litoid/util/smooth.py
litoid/util/thread_queue.py
litoid/util/timed_heap.py
litoid-0.1.0.dist-info/LICENSE
litoid-0.1.0.dist-info/METADATA
litoid-0.1.0.dist-info/WHEEL
litoid-0.1.0.dist-info/RECORD
