Metadata-Version: 2.1
Name: litoid
Version: 0.1.0
Summary: 💡Sequence DMX lighting 💡
License: MIT
Author: Tom Ritchford
Author-email: tom@swirly.com
Requires-Python: >=3.11
Classifier: License :: OSI Approved :: MIT License
Classifier: Programming Language :: Python :: 3
Classifier: Programming Language :: Python :: 3.11
Requires-Dist: clsprop (>=1.1.0)
Requires-Dist: datacls (>=4.6.0)
Requires-Dist: distinctipy (>=1.2.2)
Requires-Dist: dtyper (>=2.1.0)
Requires-Dist: ipython (>=8.12.0)
Requires-Dist: matplotlib (>=3.7.1)
Requires-Dist: mido (>=1.2.10)
Requires-Dist: numpy (>=1.24.2)
Requires-Dist: psgdemos (>=1.12.1)
Requires-Dist: pyenttec (>=1.4)
Requires-Dist: pynput (>=1.7.6)
Requires-Dist: pyperclip (>=1.8.2)
Requires-Dist: pysimplegui (>=4.60.4)
Requires-Dist: python-osc (>=1.8.1)
Requires-Dist: python-rtmidi (>=1.5.4)
Requires-Dist: simpleaudio (>=1.0.4)
Requires-Dist: tomlkit (>=0.11.6)
Requires-Dist: typer (>=0.7.0)
Requires-Dist: xmod (>=1.4.0)
